.flake8
AppImageBuilder.yml
COPYING
ChangeLog
MANIFEST.in
Makefile
README.markdown
pylintrc
pyproject.toml
setup_cxfreeze.py
tox.ini
l10n/ca.po
l10n/de.po
l10n/es.po
l10n/fr.po
l10n/messages.pot
l10n/oc.po
l10n/sv.po
l10n/uk.po
l10n/zh_Hans.po
src/paperwork.egg-info/PKG-INFO
src/paperwork.egg-info/SOURCES.txt
src/paperwork.egg-info/dependency_links.txt
src/paperwork.egg-info/entry_points.txt
src/paperwork.egg-info/requires.txt
src/paperwork.egg-info/top_level.txt
src/paperwork_gtk/__init__.py
src/paperwork_gtk/_version.py
src/paperwork_gtk/doc_selection.py
src/paperwork_gtk/docimport.py
src/paperwork_gtk/flatpak.py
src/paperwork_gtk/main.py
src/paperwork_gtk/new_doc.py
src/paperwork_gtk/print.py
src/paperwork_gtk/sync_on_start.py
src/paperwork_gtk/update_notification.py
src/paperwork_gtk/about/__init__.py
src/paperwork_gtk/about/about.glade
src/paperwork_gtk/actions/__init__.py
src/paperwork_gtk/actions/app/__init__.py
src/paperwork_gtk/actions/app/find.py
src/paperwork_gtk/actions/app/help.py
src/paperwork_gtk/actions/app/open_about.py
src/paperwork_gtk/actions/app/open_bug_report.py
src/paperwork_gtk/actions/app/open_settings.py
src/paperwork_gtk/actions/app/open_shortcuts.py
src/paperwork_gtk/actions/doc/__init__.py
src/paperwork_gtk/actions/doc/add_to_selection.py
src/paperwork_gtk/actions/doc/delete.py
src/paperwork_gtk/actions/doc/export.py
src/paperwork_gtk/actions/doc/new.py
src/paperwork_gtk/actions/doc/open_external.py
src/paperwork_gtk/actions/doc/prev_next.py
src/paperwork_gtk/actions/doc/print.py
src/paperwork_gtk/actions/doc/properties.py
src/paperwork_gtk/actions/doc/redo_ocr.py
src/paperwork_gtk/actions/docs/__init__.py
src/paperwork_gtk/actions/docs/delete.py
src/paperwork_gtk/actions/docs/export.py
src/paperwork_gtk/actions/docs/properties.py
src/paperwork_gtk/actions/docs/redo_ocr.py
src/paperwork_gtk/actions/docs/select_all.py
src/paperwork_gtk/actions/page/__init__.py
src/paperwork_gtk/actions/page/copy_text.py
src/paperwork_gtk/actions/page/delete.py
src/paperwork_gtk/actions/page/edit.py
src/paperwork_gtk/actions/page/export.py
src/paperwork_gtk/actions/page/move_inside_doc.py
src/paperwork_gtk/actions/page/print.py
src/paperwork_gtk/actions/page/redo_ocr.py
