Metadata-Version: 2.1
Name: paperwork
Version: 2.2.5
Summary: Paperwork's GTK interface
Author-email: Jerome Flesch <jflesch@openpaper.work>
License: GPL-3.0-or-later
License-File: COPYING
Requires-Dist: openpaperwork-core
Requires-Dist: openpaperwork-gtk
Requires-Dist: paperwork-backend
Requires-Dist: distro
Requires-Dist: pycountry
Requires-Dist: pyocr>=0.3.0
Requires-Dist: pyxdg>=0.25
Provides-Extra: dev
Requires-Dist: pytest; extra == "dev"
Provides-Extra: lint
Requires-Dist: flake8; extra == "lint"
